sapientml/__init__.py
sapientml/executor.py
sapientml/generator.py
sapientml/macros.py
sapientml/main.py
sapientml/model.py
sapientml/params.py
sapientml/suggestion.py
sapientml/util/__init__.py
sapientml/util/json_util.py
sapientml/util/logging.py
sapientml-0.4.15.dist-info/LICENSE
sapientml-0.4.15.dist-info/METADATA
sapientml-0.4.15.dist-info/WHEEL
sapientml-0.4.15.dist-info/RECORD
