Metadata-Version: 2.1
Name: sapientml
Version: 0.4.15
Summary: Generative AutoML for Tabular Data
Home-page: https://sapientml.io/
License: Apache-2.0
Keywords: automl
Author: The SapientML Authors
Maintainer: Kosaku Kimura
Maintainer-email: kimura.kosaku@fujitsu.com
Requires-Python: >=3.9,<3.13
Classifier: License :: OSI Approved :: Apache Software License
Classifier: Programming Language :: Python :: 3
Classifier: Programming Language :: Python :: 3.9
Classifier: Programming Language :: Python :: 3.10
Classifier: Programming Language :: Python :: 3.11
Requires-Dist: numpy (>=1.19.5,<2.0.0)
Requires-Dist: pandas (>=2.0.3,<3.0.0)
Requires-Dist: pydantic (>=2.1.1,<3.0.0)
Requires-Dist: sapientml-core
Project-URL: Documentation, https://sapientml.readthedocs.io/
Project-URL: Repository, https://github.com/sapientml/sapientml
